{
  "status": "done",
  "assets": {
    "app.0a22944039724695.hot-update.js": {
      "name": "app.0a22944039724695.hot-update.js",
      "path": "C:\\codeshare\\codeshare\\static\\dist\\app.0a22944039724695.hot-update.js",
      "publicPath": "http://localhost:8080/app.0a22944039724695.hot-update.js"
    },
    "app.0a22944039724695.hot-update.json": {
      "name": "app.0a22944039724695.hot-update.json",
      "path": "C:\\codeshare\\codeshare\\static\\dist\\app.0a22944039724695.hot-update.json",
      "publicPath": "http://localhost:8080/app.0a22944039724695.hot-update.json"
    },
    "app.113681c1f2dfbd00.hot-update.js": {
      "name": "app.113681c1f2dfbd00.hot-update.js",
      "path": "C:\\codeshare\\codeshare\\static\\dist\\app.113681c1f2dfbd00.hot-update.js",
      "publicPath": "http://localhost:8080/app.113681c1f2dfbd00.hot-update.js"
    },
    "app.113681c1f2dfbd00.hot-update.json": {
      "name": "app.113681c1f2dfbd00.hot-update.json",
      "path": "C:\\codeshare\\codeshare\\static\\dist\\app.113681c1f2dfbd00.hot-update.json",
      "publicPath": "http://localhost:8080/app.113681c1f2dfbd00.hot-update.json"
    },
    "app.52bb2090429c3deb.hot-update.js": {
      "name": "app.52bb2090429c3deb.hot-update.js",
      "path": "C:\\codeshare\\codeshare\\static\\dist\\app.52bb2090429c3deb.hot-update.js",
      "publicPath": "http://localhost:8080/app.52bb2090429c3deb.hot-update.js"
    },
    "app.52bb2090429c3deb.hot-update.json": {
      "name": "app.52bb2090429c3deb.hot-update.json",
      "path": "C:\\codeshare\\codeshare\\static\\dist\\app.52bb2090429c3deb.hot-update.json",
      "publicPath": "http://localhost:8080/app.52bb2090429c3deb.hot-update.json"
    },
    "app.7e4199b08890b36c.hot-update.js": {
      "name": "app.7e4199b08890b36c.hot-update.js",
      "path": "C:\\codeshare\\codeshare\\static\\dist\\app.7e4199b08890b36c.hot-update.js",
      "publicPath": "http://localhost:8080/app.7e4199b08890b36c.hot-update.js"
    },
    "app.7e4199b08890b36c.hot-update.json": {
      "name": "app.7e4199b08890b36c.hot-update.json",
      "path": "C:\\codeshare\\codeshare\\static\\dist\\app.7e4199b08890b36c.hot-update.json",
      "publicPath": "http://localhost:8080/app.7e4199b08890b36c.hot-update.json"
    },
    "favicon.ico": {
      "name": "favicon.ico",
      "path": "C:\\codeshare\\codeshare\\static\\dist\\favicon.ico",
      "publicPath": "http://localhost:8080/favicon.ico"
    },
    "fonts/materialdesignicons-webfont.21f691f0.ttf": {
      "name": "fonts/materialdesignicons-webfont.21f691f0.ttf",
      "path": "C:\\codeshare\\codeshare\\static\\dist\\fonts\\materialdesignicons-webfont.21f691f0.ttf",
      "publicPath": "http://localhost:8080/fonts/materialdesignicons-webfont.21f691f0.ttf"
    },
    "fonts/materialdesignicons-webfont.54b0f60d.woff2": {
      "name": "fonts/materialdesignicons-webfont.54b0f60d.woff2",
      "path": "C:\\codeshare\\codeshare\\static\\dist\\fonts\\materialdesignicons-webfont.54b0f60d.woff2",
      "publicPath": "http://localhost:8080/fonts/materialdesignicons-webfont.54b0f60d.woff2"
    },
    "fonts/materialdesignicons-webfont.5d875350.eot": {
      "name": "fonts/materialdesignicons-webfont.5d875350.eot",
      "path": "C:\\codeshare\\codeshare\\static\\dist\\fonts\\materialdesignicons-webfont.5d875350.eot",
      "publicPath": "http://localhost:8080/fonts/materialdesignicons-webfont.5d875350.eot"
    },
    "fonts/materialdesignicons-webfont.d671cbf6.woff": {
      "name": "fonts/materialdesignicons-webfont.d671cbf6.woff",
      "path": "C:\\codeshare\\codeshare\\static\\dist\\fonts\\materialdesignicons-webfont.d671cbf6.woff",
      "publicPath": "http://localhost:8080/fonts/materialdesignicons-webfont.d671cbf6.woff"
    },
    "index.html": {
      "name": "index.html",
      "path": "C:\\codeshare\\codeshare\\static\\dist\\index.html",
      "publicPath": "http://localhost:8080/index.html"
    },
    "js/app.js": {
      "name": "js/app.js",
      "path": "C:\\codeshare\\codeshare\\static\\dist\\js\\app.js",
      "publicPath": "http://localhost:8080/js/app.js"
    },
    "js/chunk-vendors.js": {
      "name": "js/chunk-vendors.js",
      "path": "C:\\codeshare\\codeshare\\static\\dist\\js\\chunk-vendors.js",
      "publicPath": "http://localhost:8080/js/chunk-vendors.js"
    },
    "js/webfontloader.js": {
      "name": "js/webfontloader.js",
      "path": "C:\\codeshare\\codeshare\\static\\dist\\js\\webfontloader.js",
      "publicPath": "http://localhost:8080/js/webfontloader.js"
    }
  },
  "chunks": {
    "app": [
      "js/chunk-vendors.js",
      "js/app.js",
      "app.52bb2090429c3deb.hot-update.js"
    ]
  },
  "publicPath": "http://localhost:8080/",
  "error": "ESLintError",
  "message": "[eslint] \nC:\\codeshare\\codeshare\\CEcapstone\\src\\App.vue\n   96:8  error  'Headerbtn' is defined but never used  no-unused-vars\n  110:5  error  'headerbtn' is not defined             no-undef\n\n✖ 2 problems (2 errors, 0 warnings)\n"
}